<?xml version="1.0" encoding="utf-8" ?>
<dwsync>
<file name="myitems_icon_01.png" server="223.26.138.11//html/" local="130916155601083984" remote="131816278800000000" Dst="0" />
<file name="myitems_icon_03.png" server="223.26.138.11//html/" local="130916155604189453" remote="131816278800000000" Dst="0" />
<file name="bg.png" server="223.26.138.11//html/" local="130795059860000000" remote="131816278800000000" Dst="0" />
<file name="icons.png" server="223.26.138.11//html/" local="131245338341067545" remote="131816278800000000" Dst="0" />
<file name="mlogo_7.png" server="223.26.138.11//html/" local="131255718062055175" remote="131816278800000000" Dst="0" />
<file name="mlogo_6.png" server="223.26.138.11//html/" local="131255718059245014" remote="131816278800000000" Dst="0" />
<file name="mlogo_01.png" server="223.26.138.11//html/" local="131255718056124836" remote="131816278800000000" Dst="0" />
<file name="mlogo_05.png" server="223.26.138.11//html/" local="131255718057424910" remote="131816278800000000" Dst="0" />
<file name="b_logo.png" server="223.26.138.11//html/" local="130916101368720703" remote="131816278800000000" Dst="0" />
<file name="myitems_icon_02.png" server="223.26.138.11//html/" local="130916155602587890" remote="131816278800000000" Dst="0" />
<file name="myitems_icon_05.png" server="223.26.138.11//html/" local="130916155606611328" remote="131816278800000000" Dst="0" />
<file name="myitems_icon_04.png" server="223.26.138.11//html/" local="130916155605498046" remote="131816278800000000" Dst="0" />
<file name="myitems_icon_06.png" server="223.26.138.11//html/" local="130916155608076171" remote="131816278800000000" Dst="0" />
<file name="login_icon.png" server="223.26.138.11//html/" local="130917703501611328" remote="131816278800000000" Dst="0" />
<file name="mem_icon.png" server="223.26.138.11//html/" local="130918531655400390" remote="131816278800000000" Dst="0" />
<file name="ip01.png" server="223.26.138.11//html/" local="131242799288069291" remote="131816278800000000" Dst="0" />
<file name="ip04.png" server="223.26.138.11//html/" local="131242816085730063" remote="131816278800000000" Dst="0" />
<file name="ip03.png" server="223.26.138.11//html/" local="131242816375266623" remote="131816278800000000" Dst="0" />
<file name="ip05.png" server="223.26.138.11//html/" local="131242801847815701" remote="131816278800000000" Dst="0" />
<file name="ip06.png" server="223.26.138.11//html/" local="131242805981612140" remote="131816278800000000" Dst="0" />
<file name="ip02.png" server="223.26.138.11//html/" local="131242799823069892" remote="131816278800000000" Dst="0" />
<file name="prof01.png" server="223.26.138.11//html/" local="131247949118863113" remote="131816278800000000" Dst="0" />
<file name="prof01_txt.png" server="223.26.138.11//html/" local="131247949446401847" remote="131816278800000000" Dst="0" />
<file name="prof02_txt.png" server="223.26.138.11//html/" local="131247949639972919" remote="131816278800000000" Dst="0" />
<file name="bgi.png" server="223.26.138.11//html/" local="130915355021884765" remote="131816278800000000" Dst="0" />
<file name="bag.png" server="223.26.138.11//html/" local="131254916357024786" remote="131816278800000000" Dst="0" />
<file name="car.png" server="223.26.138.11//html/" local="130795057500000000" remote="131816278800000000" Dst="0" />
<file name="iphone6.png" server="223.26.138.11//html/" local="131254918679637632" remote="131816278800000000" Dst="0" />
<file name="ipad2.png" server="223.26.138.11//html/" local="131255698537928459" remote="131816278800000000" Dst="0" />
<file name="earth.png" server="223.26.138.11//html/" local="131357460232739303" remote="131816278800000000" Dst="0" />
<file name="item07.jpg" server="223.26.138.11//html/" local="130803809180000000" remote="131816278800000000" Dst="0" />
<file name="loca_icon.png" server="223.26.138.11//html/" local="130918792706806640" remote="131816278800000000" Dst="0" />
<file name="logo.gif" server="223.26.138.11//html/" local="130917922647597656" remote="131816278800000000" Dst="0" />
<file name="logo.png" server="223.26.138.11//html/" local="131254925096194638" remote="131816278800000000" Dst="0" />
<file name="jupiter.png" server="223.26.138.11//html/" local="131357460235979303" remote="131816278800000000" Dst="0" />
<file name="macbook.jpg" server="223.26.138.11//html/" local="130803810400000000" remote="131816278800000000" Dst="0" />
<file name="mlogo_02.png" server="223.26.138.11//html/" local="131255718056674867" remote="131816278800000000" Dst="0" />
<file name="mlogo_03.png" server="223.26.138.11//html/" local="131255718056774873" remote="131816278800000000" Dst="0" />
<file name="macbook.png" server="223.26.138.11//html/" local="131254895587186819" remote="131816278800000000" Dst="0" />
<file name="mlogo_04.png" server="223.26.138.11//html/" local="131255718058144951" remote="131816278800000000" Dst="0" />
<file name="myitem - 복사본.png" server="223.26.138.11//html/" local="130791440340000000" remote="131816278800000000" Dst="0" />
<file name="myitem.png" server="223.26.138.11//html/" local="130791440340000000" remote="131816278800000000" Dst="0" />
<file name="myitems_icon.png" server="223.26.138.11//html/" local="130916212001074219" remote="131816278800000000" Dst="0" />
<file name="myitems_icon_07.png" server="223.26.138.11//html/" local="130916155609091796" remote="131816278800000000" Dst="0" />
<file name="myitems_logo_ani.png" server="223.26.138.11//html/" local="130917938326718750" remote="131816278800000000" Dst="0" />
<file name="notebook.png" server="223.26.138.11//html/" local="130692239100000000" remote="131816278800000000" Dst="0" />
<file name="pluto.png" server="223.26.138.11//html/" local="131357460236289303" remote="131816278800000000" Dst="0" />
<file name="prof02.png" server="223.26.138.11//html/" local="131247949259771173" remote="131816278800000000" Dst="0" />
<file name="shoes - 복사본.png" server="223.26.138.11//html/" local="131254892013072392" remote="131816278800000000" Dst="0" />
<file name="shoes.png" server="223.26.138.11//html/" local="131254893915251190" remote="131816278800000000" Dst="0" />
<file name="swirl_pattern.png" server="223.26.138.11//html/" local="130790737860000000" remote="131816278800000000" Dst="0" />
<file name="space.jpg" server="223.26.138.11//html/" local="131357460236479303" remote="131816278800000000" Dst="0" />
<file name="sun.png" server="223.26.138.11//html/" local="131357460236889303" remote="131816278800000000" Dst="0" />
<file name="watch.png" server="223.26.138.11//html/" local="131254918061852297" remote="131816278800000000" Dst="0" />
<file name="tv3.png" server="223.26.138.11//html/" local="131357476725605304" remote="131816278800000000" Dst="0" />
<file name="Untitled-1.png" server="223.26.138.11//html/" local="130803831740000000" remote="131816278800000000" Dst="0" />
</dwsync>